Metadata-Version: 2.0
Name: business-rules-ext
Version: 1.0.0
Summary: Python DSL for setting up business intelligence rules that can be configured without code
Home-page: https://github.com/maciejpolanczyk/django-business-rules-ext/
Author: Maciej Polanczyk
Author-email: maciej.polanczyk@gmail.com
License: BSD License
Platform: UNKNOWN
Classifier: Intended Audience :: Developers
Classifier: License :: OSI Approved :: BSD License
Classifier: Operating System :: OS Independent
Classifier: Programming Language :: Python
Classifier: Programming Language :: Python :: 2
Classifier: Programming Language :: Python :: 2.7
Classifier: Programming Language :: Python :: 3
Classifier: Programming Language :: Python :: 3.2
Classifier: Programming Language :: Python :: 3.3
Classifier: Programming Language :: Python :: 3.5
Classifier: Programming Language :: Python :: 3.6
